{
  "total": 47,
  "generated": "2026-04-04T23:56:03.326409",
  "photos": [
    {
      "filename": "1-1.jpg",
      "camera": "ILCE-7C",
      "lens": "85mm F1.4 DG DN | Art 020",
      "focal_length": "85.0 mm",
      "aperture": 2.5,
      "iso": 1600,
      "shutter": "1/250",
      "date": "2025:07:04 21:07:11",
      "category": "portraits"
    },
    {
      "filename": "DSC03728.jpg",
      "camera": "ILCE-7C",
      "lens": "85mm F1.4 DG DN | Art 020",
      "focal_length": "85.0 mm",
      "aperture": 2.0,
      "iso": 100,
      "shutter": "1/4000",
      "date": "2020:01:01 22:28:31",
      "category": "nature"
    },
    {
      "filename": "DSC03739.jpg",
      "camera": "ILCE-7C",
      "lens": "24-70mm F2.8 DG DN | Art 019",
      "focal_length": "33.1 mm",
      "aperture": 8.0,
      "iso": 100,
      "shutter": "1/160",
      "date": "2020:01:01 23:43:44",
      "category": "nature"
    },
    {
      "filename": "DSC03772.jpg",
      "camera": "ILCE-7C",
      "lens": "85mm F1.4 DG DN | Art 020",
      "focal_length": "85.0 mm",
      "aperture": 4.0,
      "iso": 100,
      "shutter": "1/640",
      "date": "2020:01:02 19:25:44",
      "category": "portraits"
    },
    {
      "filename": "DSC03811.jpg",
      "camera": "ILCE-7C",
      "lens": "85mm F1.4 DG DN | Art 020",
      "focal_length": "85.0 mm",
      "aperture": 1.4,
      "iso": 100,
      "shutter": "1/8000",
      "date": "2020:01:03 17:48:05",
      "category": "nature"
    },
    {
      "filename": "DSC03958.jpg",
      "camera": "ILCE-7C",
      "lens": "----",
      "focal_length": "Unknown",
      "aperture": "Unknown",
      "iso": 1600,
      "shutter": 10,
      "date": "2025:04:14 22:19:57",
      "category": "urban"
    },
    {
      "filename": "DSC03989.jpg",
      "camera": "ILCE-7C",
      "lens": "----",
      "focal_length": "Unknown",
      "aperture": "Unknown",
      "iso": 3200,
      "shutter": 25,
      "date": "2025:04:21 22:07:54",
      "category": "portraits"
    },
    {
      "filename": "DSC04013.jpg",
      "camera": "ILCE-7C",
      "lens": "----",
      "focal_length": "Unknown",
      "aperture": "Unknown",
      "iso": 4000,
      "shutter": "1/60",
      "date": "2025:04:23 20:43:15",
      "category": "nature"
    },
    {
      "filename": "DSC04039.jpg",
      "camera": "ILCE-7C",
      "lens": "----",
      "focal_length": "Unknown",
      "aperture": "Unknown",
      "iso": 4000,
      "shutter": "1/125",
      "date": "2025:04:23 21:10:25",
      "category": "urban"
    },
    {
      "filename": "GAS00869.jpg",
      "camera": "ILCE-6600",
      "lens": "FE 70-200mm F4 G OSS",
      "focal_length": "200.0 mm",
      "aperture": 6.3,
      "iso": 500,
      "shutter": 5,
      "date": "2025:01:29 18:11:38",
      "category": "portraits"
    },
    {
      "filename": "GAS00911.jpg",
      "camera": "ILCE-6600",
      "lens": "85mm F1.4 DG DN | Art 020",
      "focal_length": "85.0 mm",
      "aperture": 6.3,
      "iso": 200,
      "shutter": "1/320",
      "date": "2025:02:09 10:46:45",
      "category": "portraits"
    },
    {
      "filename": "GAS00961.jpg",
      "camera": "ILCE-6600",
      "lens": "85mm F1.4 DG DN | Art 020",
      "focal_length": "85.0 mm",
      "aperture": 1.8,
      "iso": 125,
      "shutter": "1/1250",
      "date": "2025:02:11 11:48:42",
      "category": "portraits"
    },
    {
      "filename": "GAS00965.jpg",
      "camera": "ILCE-6600",
      "lens": "85mm F1.4 DG DN | Art 020",
      "focal_length": "85.0 mm",
      "aperture": 1.4,
      "iso": 100,
      "shutter": "1/1600",
      "date": "2025:02:11 11:48:51",
      "category": "portraits"
    },
    {
      "filename": "GAS01027.jpg",
      "camera": "ILCE-6600",
      "lens": "24-70mm F2.8 DG DN | Art 019",
      "focal_length": "33.1 mm",
      "aperture": 2.8,
      "iso": 100,
      "shutter": "1/30",
      "date": "2021:03:15 14:48:38",
      "category": "nature"
    },
    {
      "filename": "GAS01736.jpg",
      "camera": "ILCE-6600",
      "lens": "24-70mm F2.8 DG DN | Art 019",
      "focal_length": "70.0 mm",
      "aperture": 5.6,
      "iso": 160,
      "shutter": "1/125",
      "date": "2021:05:25 19:43:57",
      "category": "urban"
    },
    {
      "filename": "GAS01997.jpg",
      "camera": "ILCE-6600",
      "lens": "----",
      "focal_length": "Unknown",
      "aperture": "Unknown",
      "iso": 10000,
      "shutter": "1/100",
      "date": "2025:02:27 20:51:07",
      "category": "portraits"
    },
    {
      "filename": "GAS02126.jpg",
      "camera": "ILCE-6600",
      "lens": "----",
      "focal_length": "Unknown",
      "aperture": "Unknown",
      "iso": 800,
      "shutter": "1/100",
      "date": "2025:03:01 20:37:11",
      "category": "nature"
    },
    {
      "filename": "GAS02292.jpg",
      "camera": "ILCE-6600",
      "lens": "----",
      "focal_length": "Unknown",
      "aperture": "Unknown",
      "iso": 16000,
      "shutter": 13,
      "date": "2021:07:04 00:13:08",
      "category": "urban"
    },
    {
      "filename": "GAS02556.jpg",
      "camera": "ILCE-6600",
      "lens": "----",
      "focal_length": "Unknown",
      "aperture": "Unknown",
      "iso": 100,
      "shutter": 0.3,
      "date": "2021:07:15 20:13:55",
      "category": "portraits"
    },
    {
      "filename": "GAS02655.jpg",
      "camera": "ILCE-6600",
      "lens": "85mm F1.4 DG DN | Art 020",
      "focal_length": "85.0 mm",
      "aperture": 1.4,
      "iso": 800,
      "shutter": "1/640",
      "date": "2025:03:09 16:19:41",
      "category": "portraits"
    },
    {
      "filename": "GAS03036.jpg",
      "camera": "ILCE-6600",
      "lens": "FE 70-200mm F4 G OSS",
      "focal_length": "200.0 mm",
      "aperture": 4.0,
      "iso": 1600,
      "shutter": "1/640",
      "date": "2023:08:01 18:59:05",
      "category": "portraits"
    },
    {
      "filename": "GAS03077-2.jpg",
      "camera": "ILCE-6600",
      "lens": "85mm F1.4 DG DN | Art 020",
      "focal_length": "85.0 mm",
      "aperture": 1.4,
      "iso": 1250,
      "shutter": "1/250",
      "date": "2023:08:10 19:45:31",
      "category": "portraits"
    },
    {
      "filename": "GAS03077.jpg",
      "camera": "ILCE-6600",
      "lens": "85mm F1.4 DG DN | Art 020",
      "focal_length": "85.0 mm",
      "aperture": 1.4,
      "iso": 1250,
      "shutter": "1/250",
      "date": "2023:08:10 19:45:31",
      "category": "portraits"
    },
    {
      "filename": "GAS03356.jpg",
      "camera": "ILCE-6600",
      "lens": "----",
      "focal_length": "Unknown",
      "aperture": "Unknown",
      "iso": 3200,
      "shutter": 15,
      "date": "2023:08:11 23:02:54",
      "category": "urban"
    },
    {
      "filename": "GAS03719.jpg",
      "camera": "ILCE-6600",
      "lens": "24-70mm F2.8 DG DN | Art 019",
      "focal_length": "40.7 mm",
      "aperture": 4.0,
      "iso": 100,
      "shutter": "1/1000",
      "date": "2025:04:06 11:26:21",
      "category": "portraits"
    },
    {
      "filename": "GAS04297.jpg",
      "camera": "ILCE-6600",
      "lens": "----",
      "focal_length": "Unknown",
      "aperture": "Unknown",
      "iso": 1600,
      "shutter": 20,
      "date": "2022:10:23 19:49:25",
      "category": "nature"
    },
    {
      "filename": "GAS05031.jpg",
      "camera": "ILCE-6600",
      "lens": "----",
      "focal_length": "Unknown",
      "aperture": "Unknown",
      "iso": 100,
      "shutter": "1/50",
      "date": "2023:11:19 10:06:20",
      "category": "urban"
    },
    {
      "filename": "GAS05034.jpg",
      "camera": "ILCE-6600",
      "lens": "85mm F1.4 DG DN | Art 020",
      "focal_length": "85.0 mm",
      "aperture": 1.4,
      "iso": 800,
      "shutter": "1/250",
      "date": "2023:11:27 20:19:39",
      "category": "portraits"
    },
    {
      "filename": "GAS05546.jpg",
      "camera": "ILCE-6600",
      "lens": "85mm F1.4 DG DN | Art 020",
      "focal_length": "85.0 mm",
      "aperture": 1.4,
      "iso": 100,
      "shutter": "1/250",
      "date": "2022:11:19 14:19:27",
      "category": "portraits"
    },
    {
      "filename": "GAS05559.jpg",
      "camera": "ILCE-6600",
      "lens": "85mm F1.4 DG DN | Art 020",
      "focal_length": "85.0 mm",
      "aperture": 1.4,
      "iso": 100,
      "shutter": "1/250",
      "date": "2022:11:19 14:23:45",
      "category": "portraits"
    },
    {
      "filename": "GAS05670.jpg",
      "camera": "ILCE-6600",
      "lens": "24-70mm F2.8 DG DN | Art 019",
      "focal_length": "70.0 mm",
      "aperture": 2.8,
      "iso": 100,
      "shutter": "1/500",
      "date": "2021:09:18 12:23:40",
      "category": "portraits"
    },
    {
      "filename": "GAS05948.jpg",
      "camera": "ILCE-7C",
      "lens": "24-70mm F2.8 DG DN | Art 019",
      "focal_length": "53.5 mm",
      "aperture": 8.0,
      "iso": 250,
      "shutter": "1/60",
      "date": "2025:05:04 20:07:09",
      "category": "nature"
    },
    {
      "filename": "GAS06192.jpg",
      "camera": "ILCE-6600",
      "lens": "35mm F1.4 DG HSM | Art 012",
      "focal_length": "35.0 mm",
      "aperture": 7.1,
      "iso": 200,
      "shutter": 2.5,
      "date": "2022:12:19 18:57:20",
      "category": "urban"
    },
    {
      "filename": "GAS06274.jpg",
      "camera": "ILCE-7C",
      "lens": "85mm F1.4 DG DN | Art 020",
      "focal_length": "85.0 mm",
      "aperture": 2.8,
      "iso": 10000,
      "shutter": "1/500",
      "date": "2025:05:19 20:39:18",
      "category": "portraits"
    },
    {
      "filename": "GAS06393.jpg",
      "camera": "ILCE-6600",
      "lens": "85mm F1.4 DG DN | Art 020",
      "focal_length": "85.0 mm",
      "aperture": 6.3,
      "iso": 160,
      "shutter": "1/250",
      "date": "2023:01:01 14:43:13",
      "category": "portraits"
    },
    {
      "filename": "GAS07592.jpg",
      "camera": "ILCE-7C",
      "lens": "85mm F1.4 DG DN | Art 020",
      "focal_length": "85.0 mm",
      "aperture": 1.4,
      "iso": 50,
      "shutter": "1/640",
      "date": "2025:07:05 09:56:50",
      "category": "urban"
    },
    {
      "filename": "GAS07633.jpg",
      "camera": "ILCE-7C",
      "lens": "85mm F1.4 DG DN | Art 020",
      "focal_length": "85.0 mm",
      "aperture": 8.0,
      "iso": 100,
      "shutter": "1/160",
      "date": "2025:07:05 15:11:27",
      "category": "portraits"
    },
    {
      "filename": "GAS07686.jpg",
      "camera": "ILCE-7C",
      "lens": "24-70mm F2.8 DG DN | Art 019",
      "focal_length": "70.0 mm",
      "aperture": 2.8,
      "iso": 100,
      "shutter": "1/50",
      "date": "2025:07:05 18:53:23",
      "category": "nature"
    },
    {
      "filename": "GAS08260.jpg",
      "camera": "ILCE-7C",
      "lens": "----",
      "focal_length": "Unknown",
      "aperture": "Unknown",
      "iso": 6400,
      "shutter": "1/125",
      "date": "2025:08:04 20:23:43",
      "category": "urban"
    },
    {
      "filename": "GAS08610.jpg",
      "camera": "ILCE-6600",
      "lens": "85mm F1.4 DG DN | Art 020",
      "focal_length": "85.0 mm",
      "aperture": 1.4,
      "iso": 1250,
      "shutter": "1/250",
      "date": "2023:04:28 18:41:34",
      "category": "portraits"
    },
    {
      "filename": "GAS08991.jpg",
      "camera": "ILCE-7C",
      "lens": "85mm F1.4 DG DN | Art 020",
      "focal_length": "85.0 mm",
      "aperture": 1.4,
      "iso": 1600,
      "shutter": "1/400",
      "date": "2025:08:28 19:54:44",
      "category": "nature"
    },
    {
      "filename": "GAS09039.jpg",
      "camera": "ILCE-7C",
      "lens": "85mm F1.4 DG DN | Art 020",
      "focal_length": "85.0 mm",
      "aperture": 1.4,
      "iso": 3200,
      "shutter": "1/200",
      "date": "2025:08:28 20:52:04",
      "category": "urban"
    },
    {
      "filename": "GAS09659.jpg",
      "camera": "ILCE-7C",
      "lens": "24-70mm F2.8 DG DN | Art 019",
      "focal_length": "25.7 mm",
      "aperture": 2.8,
      "iso": 8000,
      "shutter": "1/50",
      "date": "2025:10:24 20:50:36",
      "category": "portraits"
    },
    {
      "filename": "Untitled (14).jpg",
      "camera": "OpticFilm 8200i",
      "lens": "Unknown",
      "focal_length": "Unknown",
      "aperture": "Unknown",
      "iso": "Unknown",
      "shutter": "Unknown",
      "date": "Unknown",
      "category": "nature"
    },
    {
      "filename": "Untitled (25).jpg",
      "camera": "OpticFilm 8200i",
      "lens": "Unknown",
      "focal_length": "Unknown",
      "aperture": "Unknown",
      "iso": "Unknown",
      "shutter": "Unknown",
      "date": "Unknown",
      "category": "urban"
    },
    {
      "filename": "Untitled (27).jpg",
      "camera": "OpticFilm 8200i",
      "lens": "Unknown",
      "focal_length": "Unknown",
      "aperture": "Unknown",
      "iso": "Unknown",
      "shutter": "Unknown",
      "date": "Unknown",
      "category": "portraits"
    },
    {
      "filename": "Untitled (30).jpg",
      "camera": "OpticFilm 8200i",
      "lens": "Unknown",
      "focal_length": "Unknown",
      "aperture": "Unknown",
      "iso": "Unknown",
      "shutter": "Unknown",
      "date": "Unknown",
      "category": "nature"
    }
  ],
  "stats": {
    "portraits": 24,
    "nature": 12,
    "urban": 11
  }
}